a3redis/__init__.py
a3redis/advances/__init__.py
a3redis/advances/pubsub.py
a3redis/advances/script.py
a3redis/bases/__init__.py
a3redis/bases/base_on_connection.py
a3redis/bases/control_panel.py
a3redis/bases/redis_client_factory.py
a3redis/structures/__init__.py
a3redis/structures/base_structure.py
a3redis/structures/hash.py
a3redis/structures/hyper_log_log.py
a3redis/structures/list.py
a3redis/structures/set.py
a3redis/structures/sorted_set.py
a3redis/structures/string.py
a3redis-0.3.0.dist-info/LICENSE
a3redis-0.3.0.dist-info/METADATA
a3redis-0.3.0.dist-info/WHEEL
a3redis-0.3.0.dist-info/top_level.txt
a3redis-0.3.0.dist-info/RECORD
